django_message_broker/__init__.py
django_message_broker/apps.py
django_message_broker/base_channel_layer.py
django_message_broker/config.py
django_message_broker/layer.py
django_message_broker/process_client.py
django_message_broker/server/__init__.py
django_message_broker/server/channels_client.py
django_message_broker/server/channels_server.py
django_message_broker/server/client_queue.py
django_message_broker/server/data_message.py
django_message_broker/server/exceptions.py
django_message_broker/server/server_queue.py
django_message_broker/server/signalling_message.py
django_message_broker/server/socket_manager.py
django_message_broker/server/utils.py
django_message_broker-0.2.1.dist-info/LICENSE
django_message_broker-0.2.1.dist-info/WHEEL
django_message_broker-0.2.1.dist-info/METADATA
django_message_broker-0.2.1.dist-info/RECORD
