Metadata-Version: 2.1
Name: django-message-broker
Version: 0.2.1
Summary: All-in-one message broker for Django supporting Channels, Celery and process workers
Home-page: https://github.com/django-message-broker/django-message-broker
License: Apache-2.0
Keywords: django,message-broker,channels,celery
Author: Tanzo Creative Ltd
Requires-Python: >=3.8,<4.0
Classifier: Development Status :: 4 - Beta
Classifier: Environment :: Web Environment
Classifier: Framework :: Django :: 4.0
Classifier: Intended Audience :: Developers
Classifier: License :: OSI Approved :: Apache Software License
Classifier: Operating System :: OS Independent
Classifier: Programming Language :: Python :: 3
Classifier: Programming Language :: Python :: 3.10
Classifier: Programming Language :: Python :: 3.8
Classifier: Programming Language :: Python :: 3.9
Classifier: Topic :: Software Development :: Libraries
Classifier: Typing :: Typed
Provides-Extra: docs
Requires-Dist: Django (>=4.0,<5.0)
Requires-Dist: Sphinx (>=4.3.2,<5.0.0); extra == "docs"
Requires-Dist: msgspec (>=0.3.2,<0.4.0)
Requires-Dist: myst-parser (>=0.16.1,<0.17.0); extra == "docs"
Requires-Dist: pyzmq (>=22.3.0,<23.0.0)
Requires-Dist: sphinx_rtd_theme (>=1.0.0,<2.0.0); extra == "docs"
Requires-Dist: tornado (>=6.1,<7.0)
Project-URL: Documentation, https://django-message-broker.readthedocs.io/en/latest/index.html
Project-URL: Repository, https://github.com/django-message-broker/django-message-broker
